README.rst
setup.py
urlcanon/__init__.py
urlcanon/canon.py
urlcanon/parse.py
urlcanon/rules.py
urlcanon/whatwg.py
urlcanon.egg-info/PKG-INFO
urlcanon.egg-info/SOURCES.txt
urlcanon.egg-info/dependency_links.txt
urlcanon.egg-info/requires.txt
urlcanon.egg-info/top_level.txt