Metadata-Version: 1.1
Name: urlcanon
Version: 0.1.dev21
Summary: url canonicalization library for python and java
Home-page: https://github.com/iipc/urlcanon
Author: UNKNOWN
Author-email: UNKNOWN
License: UNKNOWN
Platform: UNKNOWN
Classifier: License :: OSI Approved :: Apache Software License
Classifier: Programming Language :: Python :: 2.7
Classifier: Programming Language :: Python :: 3.4
Classifier: Programming Language :: Python :: 3.5
Classifier: Programming Language :: Python :: 3.6
Classifier: Programming Language :: Java
Classifier: Topic :: Internet :: WWW/HTTP
